XSteamPython/Boundaries.py
XSteamPython/Constants.py
XSteamPython/Convert.py
XSteamPython/Region1.py
XSteamPython/Region2.py
XSteamPython/Region3.py
XSteamPython/Region4.py
XSteamPython/Region5.py
XSteamPython/Regions.py
XSteamPython/Viscosity.py
XSteamPython/XSteamPython.py
XSteamPython/__init__.py
XSteamPython-1.0.3.dist-info/LICENSE
XSteamPython-1.0.3.dist-info/METADATA
XSteamPython-1.0.3.dist-info/WHEEL
XSteamPython-1.0.3.dist-info/top_level.txt
XSteamPython-1.0.3.dist-info/RECORD
