Metadata-Version: 2.1
Name: XSteamPython
Version: 1.0.3
Summary: Port of XSteam tables by Magnus Holmgren to python
Home-page: https://github.com/raldridge11/XSteamPython
Author: Magnus Holmgren; ported by R. Aldridge
Classifier: License :: OSI Approved :: GNU General Public License v2 (GPLv2)
Classifier: Programming Language :: Python :: 3.7
Classifier: Programming Language :: Python :: 3.8
Classifier: Programming Language :: Python :: 3.9
Requires-Python: >=3.7.*
License-File: LICENSE
Requires-Dist: scipy (>=1.6.1)
